phrasetopicminer/__init__.py
phrasetopicminer/phrase_miner.py
phrasetopicminer/smoke_test.py
phrasetopicminer/topic_labeler.py
phrasetopicminer/topic_modeler.py
phrasetopicminer/topic_timeline.py
phrasetopicminer/topic_viz.py
phrasetopicminer/visualization_datamap.py
phrasetopicminer-0.2.2.dist-info/METADATA
phrasetopicminer-0.2.2.dist-info/WHEEL
phrasetopicminer-0.2.2.dist-info/licenses/LICENSE
phrasetopicminer-0.2.2.dist-info/RECORD
